requirements_installer.py
requirements_installer-1.1.1.dist-info/licenses/LICENSE
requirements_installer-1.1.1.dist-info/METADATA
requirements_installer-1.1.1.dist-info/WHEEL
requirements_installer-1.1.1.dist-info/entry_points.txt
requirements_installer-1.1.1.dist-info/top_level.txt
requirements_installer-1.1.1.dist-info/RECORD
