Metadata-Version: 2.4
Name: requirements_installer
Version: 1.1.1
Summary: Automatically detect and install Python dependencies from your code
Author-email: Sina Mirshahi <sina7th@gmail.com>
License: MIT
Project-URL: Homepage, https://github.com/FH-Prevail/requirements_installer
Project-URL: Repository, https://github.com/FH-Prevail/requirements_installer
Project-URL: Issues, https://github.com/FH-Prevail/requirements_installer/issues
Keywords: pip,requirements,dependencies,automation,installer
Classifier: Development Status :: 4 - Beta
Classifier: Intended Audience :: Developers
Classifier: License :: OSI Approved :: MIT License
Classifier: Programming Language :: Python :: 3
Classifier: Programming Language :: Python :: 3.7
Classifier: Programming Language :: Python :: 3.8
Classifier: Programming Language :: Python :: 3.9
Classifier: Programming Language :: Python :: 3.10
Classifier: Programming Language :: Python :: 3.11
Classifier: Programming Language :: Python :: 3.12
Classifier: Topic :: Software Development :: Libraries :: Python Modules
Classifier: Topic :: System :: Installation/Setup
Requires-Python: >=3.7
License-File: LICENSE
Dynamic: license-file
